Workbook

Sheet Instructions
B2: Financial Ratios Dashboard — Data Template
B3: Populated for: SkyWorld Development Berhad (Bursa Malaysia: 5325). FY ending 31 March. 4 years populated; FY2021 awaiting AR 2022.
B5: How to use this workbook
B7: 1. Open each company's Annual Report (PDF). For SkyWorld, FY ends 30 June.
B8: 2. On the 'Raw Data' sheet, type values into the YELLOW input cells only.
B9: All numbers should be in RM '000 (thousands) — keep units consistent across all 5 years.
B10: 3. Use the 'Sources' sheet as a roadmap — it tells you where each figure typically lives in a MFRS-compliant annual report.
B11: 4. The 'Ratios' sheet auto-calculates everything. Do NOT type into it.
B12: 5. The 'Risk Flags' sheet highlights any ratio with ±20% YoY movement (ISA 520 analytical-review threshold).
B13: 6. Once all 5 years are filled in, this workbook becomes the source for Power BI:
B14: Get Data → Excel Workbook → point at this file → load 'Raw Data' and 'Ratios' as tables.
B16: Cell colour key (industry standard)
... B36: • Property developers carry significant deposits / progress billings as current liabilities — these inflate the current ratio denominator.

Sheet Raw Data
A1: SkyWorld Development Berhad — Raw Financial Data (Group, RM '000, FY ending 31 March)
A2: Source: Audited Annual Reports 2023, 2024, 2025. NI = Profit for the year (group, incl. NCI < 1% of equity). Receivables include MFRS 15 contract assets. Inventory is current portion only (land bank in non-current assets).
A4: Line item | B4: FY2022 | C4: FY2023 | D4: FY2024 | E4: FY2025 | F4: (add FY2026 / earlier yr) | G4: Notes / Source
A6: INCOME STATEMENT
A7: Revenue | B7: 790437 | C7: 841411 | D7: 688038 | E7: 445489 | G7: AR Notes 3 (FY25) / 3 (FY24) / 5 (FY23): Revenue from contracts with customers (MFRS 15)
A8: Cost of sales | B8: 540830 | C8: 543065 | D8: 434620 | E8: 280128 | G8: AR Notes 4 (FY25) / 4 (FY24) / 6 (FY23)
A9: Gross profit | B9: =B7-B8 -> 249607 | C9: =C7-C8 -> 298346 | D9: =D7-D8 -> 253418 | E9: =E7-E8 -> 165361 | F9: =F7-F8 -> 0
A10: Other operating income | B10: 3141 | C10: 5838 | D10: 11739 | E10: 15605 | G10: AR Notes 5/5/7 — gains, govt grants, reversals
A11: Operating expenses (SG&A, etc.) | B11: 84988 | C11: 84634 | D11: 89058 | E11: 81744 | G11: Selling & marketing + Admin expenses (combined)
A12: EBIT (Operating profit) | B12: =B9+B10-B11 -> 167760 | C12: =C9+C10-C11 -> 219550 | D12: =D9+D10-D11 -> 176099 | E12: =E9+E10-E11 -> 99222 | F12: =F9+F10-F11 -> 0
A13: Finance costs (net) | B13: 17743 | C13: 14766 | D13: 16164 | E13: 14670 | G13: AR Notes 6/6/8
A14: Profit before tax | B14: =B12-B13 -> 150017 | C14: =C12-C13 -> 204784 | D14: =D12-D13 -> 159935 | E14: =E12-E13 -> 84552 | F14: =F12-F13 -> 0
A15: Income tax expense | B15: 45733 | C15: 54073 | D15: 53424 | E15: 28465 | G15: AR Notes 9/9/11
A16: Net income (PAT attributable to owners) | B16: =B14-B15 -> 104284 | C16: =C14-C15 -> 150711 | D16: =D14-D15 -> 106511 | E16: =E14-E15 -> 56087 | F16: =F14-F15 -> 0
A18: BALANCE SHEET — ASSETS
A19: Cash & cash equivalents | B19: 280472 | C19: 237727 | D19: 499922 | E19: 349621 | G19: Cash and bank balances — current assets
A20: Trade & other receivables | B20: 247123 | C20: 232503 | D20: 211546 | E20: 281126 | G20: Trade rec + Contract assets + Contract cost assets + Other receivables
A21: Inventory (incl. property dev. costs + unsold completed) | B21: 276634 | C21: 184441 | D21: 190639 | E21: 265935 | G21: Property development costs + Completed properties (current only — excl. NC land bank)
A22: Other current assets | B22: 4125 | C22: 12585 | D22: 15317 | E22: 16326 | G22: Current tax assets
A23: Total current assets | B23: =SUM(B19:B22) -> 808354 | C23: =SUM(C19:C22) -> 667256 | D23: =SUM(D19:D22) -> 917424 | E23: =SUM(E19:E22) -> 913008 | F23: =SUM(F19:F22) -> 0
A24: Non-current assets (PPE, investments, etc.) | B24: 556246 | C24: 650413 | D24: 641225 | E24: 618018 | G24: Includes ~RM498-548m land held for property development (NC inventory)
A25: Total assets | B25: =B23+B24 -> 1364600 | C25: =C23+C24 -> 1317669 | D25: =D23+D24 -> 1558649 | E25: =E23+E24 -> 1531026 | F25: =F23+F24 -> 0
A27: BALANCE SHEET — LIABILITIES & EQUITY
A28: Trade & other payables | B28: 250729 | C28: 212370 | D28: 196142 | E28: 189751 | G28: Trade payables + Other payables & accrued expenses
A29: Short-term borrowings | B29: 158225 | C29: 159196 | D29: 213415 | E29: 260384 | G29: Bank borrowings — current portion
A30: Other current liabilities (incl. progress billings) | B30: 199880 | C30: 5578 | D30: 18933 | E30: 4765 | G30: Contract liab + Land costs payable + Lease liab (CL) + Current tax liab
A31: Total current liabilities | B31: =SUM(B28:B30) -> 608834 | C31: =SUM(C28:C30) -> 377144 | D31: =SUM(D28:D30) -> 428490 | E31: =SUM(E28:E30) -> 454900 | F31: =SUM(F28:F30) -> 0
A32: Long-term borrowings | B32: 289796 | C32: 323927 | D32: 276142 | E32: 188856 | G32: Bank borrowings — non-current portion
A33: Other non-current liabilities | B33: 914 | C33: 938 | D33: 11182 | E33: 7275 | G33: Lease liab (NC) + Land costs payable (NC) + Deferred tax liab
A34: Total non-current liabilities | B34: =B32+B33 -> 290710 | C34: =C32+C33 -> 324865 | D34: =D32+D33 -> 287324 | E34: =E32+E33 -> 196131 | F34: =F32+F33 -> 0
A35: Total liabilities | B35: =B31+B34 -> 899544 | C35: =C31+C34 -> 702009 | D35: =D31+D34 -> 715814 | E35: =E31+E34 -> 651031 | F35: =F31+F34 -> 0
A36: Total equity (attributable to owners) | B36: 465056 | C36: 615660 | D36: 842833 | E36: 879995 | G36: Total Equity incl. NCI (NCI immaterial: <1% of equity) for balance-sheet identity
A37: Total equity + liabilities (check vs. total assets) | B37: =B36+B35 -> 1364600 | C37: =C36+C35 -> 1317669 | D37: =D36+D35 -> 1558647 | E37: =E36+E35 -> 1531026 | F37: =F36+F35 -> 0
A38: Balance check (should be 0) | B38: =B25-B37 -> 0 | C38: =C25-C37 -> 0 | D38: =D25-D37 -> 2 | E38: =E25-E37 -> 0 | F38: =F25-F37 -> 0

Sheet Ratios
A1: Calculated Ratios
A2: All formulas — do not type into these cells. Greys-out where prior-year data is needed for averages (FY2021 column).
A4: Ratio | B4: FY2022 | C4: FY2023 | D4: FY2024 | E4: FY2025 | G4: Format
A6: PROFITABILITY
A7: Gross margin % | B7: =IFERROR('Raw Data'!B9/'Raw Data'!B7,"") -> 0.31578355 | C7: =IFERROR('Raw Data'!C9/'Raw Data'!C7,"") -> 0.3545782 | D7: =IFERROR('Raw Data'!D9/'Raw Data'!D7,"") -> 0.36831977 | E7: =IFERROR('Raw Data'!E9/'Raw Data'!E7,"") -> 0.37118986 | F7: =IFERROR('Raw Data'!F9/'Raw Data'!F7,"") | G7: %
A8: EBIT margin % | B8: =IFERROR('Raw Data'!B12/'Raw Data'!B7,"") -> 0.21223703 | C8: =IFERROR('Raw Data'!C12/'Raw Data'!C7,"") -> 0.26093075 | D8: =IFERROR('Raw Data'!D12/'Raw Data'!D7,"") -> 0.25594371 | E8: =IFERROR('Raw Data'!E12/'Raw Data'!E7,"") -> 0.22272604 | F8: =IFERROR('Raw Data'!F12/'Raw Data'!F7,"") | G8: %
A9: Net margin % | B9: =IFERROR('Raw Data'!B16/'Raw Data'!B7,"") -> 0.13193208 | C9: =IFERROR('Raw Data'!C16/'Raw Data'!C7,"") -> 0.17911698 | D9: =IFERROR('Raw Data'!D16/'Raw Data'!D7,"") -> 0.15480395 | E9: =IFERROR('Raw Data'!E16/'Raw Data'!E7,"") -> 0.12589985 | F9: =IFERROR('Raw Data'!F16/'Raw Data'!F7,"") | G9: %
A10: Return on Equity (ROE) — avg equity | C10: =IFERROR('Raw Data'!C16/AVERAGE('Raw Data'!C36,'Raw Data'!B36),"") -> 0.27890954 | D10: =IFERROR('Raw Data'!D16/AVERAGE('Raw Data'!D36,'Raw Data'!C36),"") -> 0.14605624 | E10: =IFERROR('Raw Data'!E16/AVERAGE('Raw Data'!E36,'Raw Data'!D36),"") -> 0.065110388 | F10: =IFERROR('Raw Data'!F16/AVERAGE('Raw Data'!F36,'Raw Data'!E36),"") -> 0 | G10: %
A11: Return on Assets (ROA) — avg assets | C11: =IFERROR('Raw Data'!C16/AVERAGE('Raw Data'!C25,'Raw Data'!B25),"") -> 0.11237575 | D11: =IFERROR('Raw Data'!D16/AVERAGE('Raw Data'!D25,'Raw Data'!C25),"") -> 0.074060657 | E11: =IFERROR('Raw Data'!E16/AVERAGE('Raw Data'!E25,'Raw Data'!D25),"") -> 0.036306084 | F11: =IFERROR('Raw Data'!F16/AVERAGE('Raw Data'!F25,'Raw Data'!E25),"") -> 0 | G11: %
A13: LIQUIDITY
A14: Current ratio | B14: =IFERROR('Raw Data'!B23/'Raw Data'!B31,"") -> 1.3277084 | C14: =IFERROR('Raw Data'!C23/'Raw Data'!C31,"") -> 1.769234 | D14: =IFERROR('Raw Data'!D23/'Raw Data'!D31,"") -> 2.1410628 | E14: =IFERROR('Raw Data'!E23/'Raw Data'!E31,"") -> 2.0070521 | F14: =IFERROR('Raw Data'!F23/'Raw Data'!F31,"") | G14: x
A15: Quick ratio (acid test) | B15: =IFERROR(('Raw Data'!B23-'Raw Data'!B21)/'Raw Data'!B31,"") -> 0.8733415 | C15: =IFERROR(('Raw Data'!C23-'Raw Data'!C21)/'Raw Data'!C31,"") -> 1.2801874 | D15: =IFERROR(('Raw Data'!D23-'Raw Data'!D21)/'Raw Data'!D31,"") -> 1.6961539 | E15: =IFERROR(('Raw Data'!E23-'Raw Data'!E21)/'Raw Data'!E31,"") -> 1.4224511 | F15: =IFERROR(('Raw Data'!F23-'Raw Data'!F21)/'Raw Data'!F31,"") | G15: x
A16: Cash ratio | B16: =IFERROR('Raw Data'!B19/'Raw Data'!B31,"") -> 0.46067072 | C16: =IFERROR('Raw Data'!C19/'Raw Data'!C31,"") -> 0.63033483 | D16: =IFERROR('Raw Data'!D19/'Raw Data'!D31,"") -> 1.1667063 | E16: =IFERROR('Raw Data'!E19/'Raw Data'!E31,"") -> 0.76856672 | F16: =IFERROR('Raw Data'!F19/'Raw Data'!F31,"") | G16: x
A17: Working capital (RM '000) | B17: ='Raw Data'!B23-'Raw Data'!B31 -> 199520 | C17: ='Raw Data'!C23-'Raw Data'!C31 -> 290112 | D17: ='Raw Data'!D23-'Raw Data'!D31 -> 488934 | E17: ='Raw Data'!E23-'Raw Data'!E31 -> 458108 | F17: ='Raw Data'!F23-'Raw Data'!F31 -> 0 | G17: RM '000
A19: LEVERAGE / GEARING
A20: Debt-to-equity (total debt / equity) | B20: =IFERROR(('Raw Data'!B29+'Raw Data'!B32)/'Raw Data'!B36,"") -> 0.96337 | C20: =IFERROR(('Raw Data'!C29+'Raw Data'!C32)/'Raw Data'!C36,"") -> 0.78472371 | D20: =IFERROR(('Raw Data'!D29+'Raw Data'!D32)/'Raw Data'!D36,"") -> 0.58084698 | E20: =IFERROR(('Raw Data'!E29+'Raw Data'!E32)/'Raw Data'!E36,"") -> 0.5105029 | F20: =IFERROR(('Raw Data'!F29+'Raw Data'!F32)/'Raw Data'!F36,"") | G20: x
A21: Total liabilities / equity | B21: =IFERROR('Raw Data'!B35/'Raw Data'!B36,"") -> 1.9342703 | C21: =IFERROR('Raw Data'!C35/'Raw Data'!C36,"") -> 1.1402544 | D21: =IFERROR('Raw Data'!D35/'Raw Data'!D36,"") -> 0.84929517 | E21: =IFERROR('Raw Data'!E35/'Raw Data'!E36,"") -> 0.73981216 | F21: =IFERROR('Raw Data'!F35/'Raw Data'!F36,"") | G21: x
A22: Net gearing ((debt-cash)/equity) | B22: =IFERROR(('Raw Data'!B29+'Raw Data'!B32-'Raw Data'!B19)/'Raw Data'!B36,"") -> 0.36027704 | C22: =IFERROR(('Raw Data'!C29+'Raw Data'!C32-'Raw Data'!C19)/'Raw Data'!C36,"") -> 0.39859013 | D22: =IFERROR(('Raw Data'!D29+'Raw Data'!D32-'Raw Data'!D19)/'Raw Data'!D36,"") -> -0.01229781 | E22: =IFERROR(('Raw Data'!E29+'Raw Data'!E32-'Raw Data'!E19)/'Raw Data'!E36,"") -> 0.11320405 | F22: =IFERROR(('Raw Data'!F29+'Raw Data'!F32-'Raw Data'!F19)/'Raw Data'!F36,"") | G22: x
A23: Interest coverage (EBIT / finance cost) | B23: =IFERROR('Raw Data'!B12/'Raw Data'!B13,"") -> 9.4549963 | C23: =IFERROR('Raw Data'!C12/'Raw Data'!C13,"") -> 14.868617 | D23: =IFERROR('Raw Data'!D12/'Raw Data'!D13,"") -> 10.894519 | E23: =IFERROR('Raw Data'!E12/'Raw Data'!E13,"") -> 6.7635992 | F23: =IFERROR('Raw Data'!F12/'Raw Data'!F13,"") | G23: x
A25: ACTIVITY / WORKING-CAPITAL DAYS
A26: Days Sales Outstanding (DSO) — avg AR | C26: =IFERROR(AVERAGE('Raw Data'!C20,'Raw Data'!B20)/'Raw Data'!C7*365,"") -> 104.02971 | D26: =IFERROR(AVERAGE('Raw Data'!D20,'Raw Data'!C20)/'Raw Data'!D7*365,"") -> 117.78266 | E26: =IFERROR(AVERAGE('Raw Data'!E20,'Raw Data'!D20)/'Raw Data'!E7*365,"") -> 201.82909 | F26: =IFERROR(AVERAGE('Raw Data'!F20,'Raw Data'!E20)/'Raw Data'!F7*365,"") | G26: days
A27: Days Inventory Outstanding (DIO) — avg Inv | C27: =IFERROR(AVERAGE('Raw Data'!C21,'Raw Data'!B21)/'Raw Data'!C8*365,"") -> 154.94681 | D27: =IFERROR(AVERAGE('Raw Data'!D21,'Raw Data'!C21)/'Raw Data'!D8*365,"") -> 157.49873 | E27: =IFERROR(AVERAGE('Raw Data'!E21,'Raw Data'!D21)/'Raw Data'!E8*365,"") -> 297.45243 | F27: =IFERROR(AVERAGE('Raw Data'!F21,'Raw Data'!E21)/'Raw Data'!F8*365,"") | G27: days
A28: Days Payable Outstanding (DPO) — avg AP | C28: =IFERROR(AVERAGE('Raw Data'!C28,'Raw Data'!B28)/'Raw Data'!C8*365,"") -> 155.62698 | D28: =IFERROR(AVERAGE('Raw Data'!D28,'Raw Data'!C28)/'Raw Data'!D8*365,"") -> 171.53707 | E28: =IFERROR(AVERAGE('Raw Data'!E28,'Raw Data'!D28)/'Raw Data'!E8*365,"") -> 251.40462 | F28: =IFERROR(AVERAGE('Raw Data'!F28,'Raw Data'!E28)/'Raw Data'!F8*365,"") | G28: days
A29: Cash Conversion Cycle (DSO+DIO-DPO) | C29: =IFERROR(C26+C27-C28,"") -> 103.34954 | D29: =IFERROR(D26+D27-D28,"") -> 103.74432 | E29: =IFERROR(E26+E27-E28,"") -> 247.87691 | F29: =IFERROR(F26+F27-F28,"") | G29: days
A31: GROWTH (YoY)
A32: Revenue growth % | C32: =IFERROR('Raw Data'!C7/'Raw Data'!B7-1,"") -> 0.064488378 | D32: =IFERROR('Raw Data'!D7/'Raw Data'!C7-1,"") -> -0.18228072 | E32: =IFERROR('Raw Data'!E7/'Raw Data'!D7-1,"") -> -0.35252268 | F32: =IFERROR('Raw Data'!F7/'Raw Data'!E7-1,"") -> -1 | G32: %
A33: EBIT growth % | C33: =IFERROR('Raw Data'!C12/'Raw Data'!B12-1,"") -> 0.30871483 | D33: =IFERROR('Raw Data'!D12/'Raw Data'!C12-1,"") -> -0.19790936 | E33: =IFERROR('Raw Data'!E12/'Raw Data'!D12-1,"") -> -0.43655557 | F33: =IFERROR('Raw Data'!F12/'Raw Data'!E12-1,"") -> -1 | G33: %
A34: Net income growth % | C34: =IFERROR('Raw Data'!C16/'Raw Data'!B16-1,"") -> 0.44519773 | D34: =IFERROR('Raw Data'!D16/'Raw Data'!C16-1,"") -> -0.29327654 | E34: =IFERROR('Raw Data'!E16/'Raw Data'!D16-1,"") -> -0.47341589 | F34: =IFERROR('Raw Data'!F16/'Raw Data'!E16-1,"") -> -1 | G34: %

Sheet Risk Flags
A1: Analytical Review — YoY Change vs ±20% Threshold (ISA 520)
A2: Red = |Δ| > 20% (investigate). Amber = 10–20%. Green = stable. Empty = first year / not applicable.
A4: Ratio | B4: FY23 vs FY22 | C4: FY24 vs FY23 | D4: FY25 vs FY24
A6: Gross margin % | B6: =IFERROR((Ratios!C7-Ratios!B7)/ABS(Ratios!B7),"") -> 0.12285205 | C6: =IFERROR((Ratios!D7-Ratios!C7)/ABS(Ratios!C7),"") -> 0.038754696 | D6: =IFERROR((Ratios!E7-Ratios!D7)/ABS(Ratios!D7),"") -> 0.007792381 | E6: =IFERROR((Ratios!F7-Ratios!E7)/ABS(Ratios!E7),"")
A7: EBIT margin % | B7: =IFERROR((Ratios!C8-Ratios!B8)/ABS(Ratios!B8),"") -> 0.22943083 | C7: =IFERROR((Ratios!D8-Ratios!C8)/ABS(Ratios!C8),"") -> -0.01911248 | D7: =IFERROR((Ratios!E8-Ratios!D8)/ABS(Ratios!D8),"") -> -0.12978508 | E7: =IFERROR((Ratios!F8-Ratios!E8)/ABS(Ratios!E8),"")
A8: Net margin % | B8: =IFERROR((Ratios!C9-Ratios!B9)/ABS(Ratios!B9),"") -> 0.35764538 | C8: =IFERROR((Ratios!D9-Ratios!C9)/ABS(Ratios!C9),"") -> -0.13573829 | D8: =IFERROR((Ratios!E9-Ratios!D9)/ABS(Ratios!D9),"") -> -0.1867142 | E8: =IFERROR((Ratios!F9-Ratios!E9)/ABS(Ratios!E9),"")
A9: Return on Equity (ROE) — avg equity | B9: =IFERROR((Ratios!C10-Ratios!B10)/ABS(Ratios!B10),"") | C9: =IFERROR((Ratios!D10-Ratios!C10)/ABS(Ratios!C10),"") -> -0.47633115 | D9: =IFERROR((Ratios!E10-Ratios!D10)/ABS(Ratios!D10),"") -> -0.55421015 | E9: =IFERROR((Ratios!F10-Ratios!E10)/ABS(Ratios!E10),"") -> -1
A10: Return on Assets (ROA) — avg assets | B10: =IFERROR((Ratios!C11-Ratios!B11)/ABS(Ratios!B11),"") | C10: =IFERROR((Ratios!D11-Ratios!C11)/ABS(Ratios!C11),"") -> -0.34095519 | D10: =IFERROR((Ratios!E11-Ratios!D11)/ABS(Ratios!D11),"") -> -0.50977907 | E10: =IFERROR((Ratios!F11-Ratios!E11)/ABS(Ratios!E11),"") -> -1
A11: Current ratio | B11: =IFERROR((Ratios!C14-Ratios!B14)/ABS(Ratios!B14),"") -> 0.33254717 | C11: =IFERROR((Ratios!D14-Ratios!C14)/ABS(Ratios!C14),"") -> 0.2101637 | D11: =IFERROR((Ratios!E14-Ratios!D14)/ABS(Ratios!D14),"") -> -0.062590739 | E11: =IFERROR((Ratios!F14-Ratios!E14)/ABS(Ratios!E14),"")
A12: Quick ratio (acid test) | B12: =IFERROR((Ratios!C15-Ratios!B15)/ABS(Ratios!B15),"") -> 0.46584973 | C12: =IFERROR((Ratios!D15-Ratios!C15)/ABS(Ratios!C15),"") -> 0.32492628 | D12: =IFERROR((Ratios!E15-Ratios!D15)/ABS(Ratios!D15),"") -> -0.16136675 | E12: =IFERROR((Ratios!F15-Ratios!E15)/ABS(Ratios!E15),"")
A13: Cash ratio | B13: =IFERROR((Ratios!C16-Ratios!B16)/ABS(Ratios!B16),"") -> 0.368298 | C13: =IFERROR((Ratios!D16-Ratios!C16)/ABS(Ratios!C16),"") -> 0.85093109 | D13: =IFERROR((Ratios!E16-Ratios!D16)/ABS(Ratios!D16),"") -> -0.34125093 | E13: =IFERROR((Ratios!F16-Ratios!E16)/ABS(Ratios!E16),"")
A14: Debt-to-equity (total debt / equity) | B14: =IFERROR((Ratios!C20-Ratios!B20)/ABS(Ratios!B20),"") -> -0.18543892 | C14: =IFERROR((Ratios!D20-Ratios!C20)/ABS(Ratios!C20),"") -> -0.25980703 | D14: =IFERROR((Ratios!E20-Ratios!D20)/ABS(Ratios!D20),"") -> -0.12110604 | E14: =IFERROR((Ratios!F20-Ratios!E20)/ABS(Ratios!E20),"")
A15: Net gearing ((debt-cash)/equity) | B15: =IFERROR((Ratios!C22-Ratios!B22)/ABS(Ratios!B22),"") -> 0.10634341 | C15: =IFERROR((Ratios!D22-Ratios!C22)/ABS(Ratios!C22),"") -> -1.0308533 | D15: =IFERROR((Ratios!E22-Ratios!D22)/ABS(Ratios!D22),"") -> 10.205221 | E15: =IFERROR((Ratios!F22-Ratios!E22)/ABS(Ratios!E22),"")
A16: Interest coverage (EBIT / finance cost) | B16: =IFERROR((Ratios!C23-Ratios!B23)/ABS(Ratios!B23),"") -> 0.5725672 | C16: =IFERROR((Ratios!D23-Ratios!C23)/ABS(Ratios!C23),"") -> -0.26728097 | D16: =IFERROR((Ratios!E23-Ratios!D23)/ABS(Ratios!D23),"") -> -0.37917412 | E16: =IFERROR((Ratios!F23-Ratios!E23)/ABS(Ratios!E23),"")
A17: Days Sales Outstanding (DSO) — avg AR | B17: =IFERROR((Ratios!C26-Ratios!B26)/ABS(Ratios!B26),"") | C17: =IFERROR((Ratios!D26-Ratios!C26)/ABS(Ratios!C26),"") -> 0.13220206 | D17: =IFERROR((Ratios!E26-Ratios!D26)/ABS(Ratios!D26),"") -> 0.71357226 | E17: =IFERROR((Ratios!F26-Ratios!E26)/ABS(Ratios!E26),"")
A18: Days Inventory Outstanding (DIO) — avg Inv | B18: =IFERROR((Ratios!C27-Ratios!B27)/ABS(Ratios!B27),"") | C18: =IFERROR((Ratios!D27-Ratios!C27)/ABS(Ratios!C27),"") -> 0.016469704 | D18: =IFERROR((Ratios!E27-Ratios!D27)/ABS(Ratios!D27),"") -> 0.88860205 | E18: =IFERROR((Ratios!F27-Ratios!E27)/ABS(Ratios!E27),"")
A19: Days Payable Outstanding (DPO) — avg AP | B19: =IFERROR((Ratios!C28-Ratios!B28)/ABS(Ratios!B28),"") | C19: =IFERROR((Ratios!D28-Ratios!C28)/ABS(Ratios!C28),"") -> 0.10223217 | D19: =IFERROR((Ratios!E28-Ratios!D28)/ABS(Ratios!D28),"") -> 0.46559937 | E19: =IFERROR((Ratios!F28-Ratios!E28)/ABS(Ratios!E28),"")
A20: Cash Conversion Cycle (DSO+DIO-DPO) | B20: =IFERROR((Ratios!C29-Ratios!B29)/ABS(Ratios!B29),"") | C20: =IFERROR((Ratios!D29-Ratios!C29)/ABS(Ratios!C29),"") -> 0.0038199113 | D20: =IFERROR((Ratios!E29-Ratios!D29)/ABS(Ratios!D29),"") -> 1.3893057 | E20: =IFERROR((Ratios!F29-Ratios!E29)/ABS(Ratios!E29),"")
A23: Legend
A24: |Δ| > 20% → RED — investigate (analytical-review threshold breached)
A25: 10–20% → AMBER — note in working papers
A26: < 10% → GREEN — within expectation

Sheet Sources
A1: Where to find each figure in the Annual Report (MFRS / Bursa Malaysia listed cos.)
A3: Line item | B3: Primary statement | C3: Typical note / location
A4: Revenue | B4: Statement of P&L | C4: First line — often disaggregated by segment in Note (Revenue from contracts with customers, MFRS 15)
A5: Cost of sales | B5: Statement of P&L | C5: Usually shown directly below revenue
A6: Other operating income | B6: Statement of P&L | C6: Includes gains on disposals, govt grants, reversal of impairments
A7: Operating expenses | B7: Statement of P&L | C7: Admin + Selling & marketing + other operating costs (sometimes shown by function, sometimes by nature)
A8: Finance costs (net) | B8: Statement of P&L | C8: Net of finance income; expand in Note on Finance Costs
A9: Income tax expense | B9: Statement of P&L | C9: Reconciliation typically in tax note
A10: Net income (PAT to owners) | B10: Statement of P&L | C10: Profit attributable to owners of the parent — NOT total comprehensive income
A11: Cash & cash equivalents | B11: Statement of Financial Position | C11: Bottom of current assets; check Note for restricted cash, fixed deposits >3m
A12: Trade & other receivables | B12: Statement of Financial Position | C12: Note breaks out: trade receivables, contract assets, deposits, prepayments. Include trade + contract assets in DSO.
A13: Inventory | B13: Statement of Financial Position | C13: For developers: Property Development Costs (Note) + Completed properties held for sale + Land held for development
A14: Total current assets | B14: Statement of Financial Position | C14: Subtotal — verify against your inputs
... A21: Total equity | B21: Statement of Financial Position | C21: Equity attributable to owners — exclude non-controlling interests (NCI) from this line
